Workbook

Sheet Monthly Plan
B3: IQRA — November 2026 to March 2027 budget (USD)
C4: Month 1 | D4: Month 2 | E4: Month 3 | F4: Month 4 | G4: Month 5
C5: Nov 2026 | D5: Dec 2026 | E5: Jan 2027 | F5: Feb 2027 | G5: Mar 2027 | H5: Nov–Mar total
B6: Peak concurrent users | C6: 1000 | D6: 2000 | E6: 4000 | F6: 8000 | G6: 16000 | H6: 16000
B7: End-month MAU required | C7: ='Usage and Acquisition'!F2 -> 90000 | D7: ='Usage and Acquisition'!F3 -> 180000 | E7: ='Usage and Acquisition'!F4 -> 360000 | F7: ='Usage and Acquisition'!F5 -> 720000 | G7: ='Usage and Acquisition'!F6 -> 1440000 | H7: 1440000
B8: Expenses
B9: Tech — software development | C9: 15000 | D9: 18000 | E9: 15000 | F9: 12000 | G9: 10000 | H9: =SUM(C9:G9) -> 70000
B10: Promotion — paid advertising | C10: ='Usage and Acquisition'!I2 -> 189000 | D10: ='Usage and Acquisition'!I3 -> 207900 | E10: ='Usage and Acquisition'!I4 -> 415800 | F10: ='Usage and Acquisition'!I5 -> 831600 | G10: ='Usage and Acquisition'!I6 -> 1663200 | H10: =SUM(C10:G10) -> 3307500
B11: Isnad board / scholar review | C11: 3000 | D11: 4000 | E11: 6000 | F11: 8000 | G11: 10000 | H11: =SUM(C11:G11) -> 31000
B12: HR — nontechnical operations & support | C12: =2000+C7/10000*Assumptions!B19 -> 3350 | D12: =2000+D7/10000*Assumptions!B19 -> 4700 | E12: =2000+E7/10000*Assumptions!B19 -> 7400 | F12: =2000+F7/10000*Assumptions!B19 -> 12800 | G12: =2000+G7/10000*Assumptions!B19 -> 23600 | H12: =SUM(C12:G12) -> 51850
B13: Partnerships / source rights | C13: 1000 | D13: 2000 | E13: 3000 | F13: 5000 | G13: 8000 | H13: =SUM(C13:G13) -> 19000
B14: Legal, company & app-store setup | C14: ='Legal and Setup'!B11 -> 6030.95 | D14: ='Legal and Setup'!C11 -> 1700 | E14: ='Legal and Setup'!D11 -> 800 | F14: ='Legal and Setup'!E11 -> 400 | G14: ='Legal and Setup'!F11 -> 400 | H14: =SUM(C14:G14) -> 9330.95
B15: Reserve — 20% contingency | C15: =C21*Assumptions!B12 -> 52436.19 | D15: =D21*Assumptions!B12 -> 66248 | E15: =E21*Assumptions!B12 -> 125916 | F15: =F21*Assumptions!B12 -> 239968.8 | G15: =G21*Assumptions!B12 -> 484544 | H15: =SUM(C15:G15) -> 969112.99
B16: AI answer generation | C16: ='Usage and Acquisition'!K2 -> 21600 | D16: ='Usage and Acquisition'!K3 -> 66960 | E16: ='Usage and Acquisition'!K4 -> 133920 | F16: ='Usage and Acquisition'!K5 -> 241920 | G16: ='Usage and Acquisition'!K6 -> 535680 | H16: =SUM(C16:G16) -> 1000080
B17: Hosting / database / monitoring | C17: =Assumptions!B18+'Usage and Acquisition'!J2/1000*Assumptions!B17 -> 1580 | D17: =Assumptions!B18+'Usage and Acquisition'!J3/1000*Assumptions!B17 -> 3848 | E17: =Assumptions!B18+'Usage and Acquisition'!J4/1000*Assumptions!B17 -> 7196 | F17: =Assumptions!B18+'Usage and Acquisition'!J5/1000*Assumptions!B17 -> 12596 | G17: =Assumptions!B18+'Usage and Acquisition'!J6/1000*Assumptions!B17 -> 27284 | H17: =SUM(C17:G17) -> 52504
B18: App maintenance / QA / security | C18: 2000 | D18: 3000 | E18: 4500 | F18: 6000 | G18: 8000 | H18: =SUM(C18:G18) -> 23500
B19: Ad creative & campaign management | C19: =1500+C10*8% -> 16620 | D19: =1500+D10*8% -> 18132 | E19: =1500+E10*8% -> 34764 | F19: =1500+F10*8% -> 68028 | G19: =1500+G10*8% -> 134556 | H19: =SUM(C19:G19) -> 272100
B20: Tools, insurance & devices | C20: 3000 | D20: 1000 | E20: 1200 | F20: 1500 | G20: 2000 | H20: =SUM(C20:G20) -> 8700
B21: Operating subtotal | C21: =SUM(C9:C14,C16:C20) -> 262180.95 | D21: =SUM(D9:D14,D16:D20) -> 331240 | E21: =SUM(E9:E14,E16:E20) -> 629580 | F21: =SUM(F9:F14,F16:F20) -> 1199844 | G21: =SUM(G9:G14,G16:G20) -> 2422720 | H21: =SUM(C21:G21) -> 4845565
B22: Total cash budget | C22: =C21+C15 -> 314617.14 | D22: =D21+D15 -> 397488 | E22: =E21+E15 -> 755496 | F22: =F21+F15 -> 1439812.8 | G22: =G21+G15 -> 2907264 | H22: =SUM(C22:G22) -> 5814677.9
B23: Cumulative cash budget | C23: =SUM($C22:C22) -> 314617.14 | D23: =SUM($C22:D22) -> 712105.14 | E23: =SUM($C22:E22) -> 1467601.1 | F23: =SUM($C22:F22) -> 2907413.9 | G23: =SUM($C22:G22) -> 5814677.9
B25: April–October intentionally not budgeted. Original Template preserves the uploaded sheet unchanged.
B26: Estimates, not vendor quotes or a capacity guarantee. No revenue, subscriptions or profit assumed.
B27: Peak targets are month-end; usage costs use a linear within-month ramp. March full run-rate AI cost is higher.

Sheet Original Template
B3: IQRA Yearly plan
C4: Month 1 | D4: Month 2 | E4: Month 3 | F4: Month 4 | G4: Month 5 | H4: Month 6 | I4: Month 7 | J4: Month 8 | K4: Month 9 | L4: Month 10 | M4: Month 11 | N4: Month 12
C5: Nov | D5: Dec | E5: Jan | F5: Feb | G5: Mar | H5: Apr | I5: May | J5: Jun | K5: Jul | L5: Aug | M5: Sep | N5: Oct
B6: User | C6: 1000 | D6: =C6*2 | E6: =D6*2 | F6: =E6*2 | G6: =F6*2 | H6: =G6*2 | I6: =H6*2 | J6: =I6*2 | K6: =J6*2 | ... N6: =M6*2 | O6: =SUM(C6:N6) | P6: 4095000
B7: KPI
B8: Expenses
B9: Tech
B10: Promotion
B11: Isnad board
B12: HR
B13: Partnership
B14: Legal
B15: Reserve

Sheet Assumptions
A1: IQRA operating budget — editable planning inputs | B1: Value | C1: Basis / scope
A2: Peak / average concurrent ratio | B2: 4 | C2: Peak online users / 24-hour average; assumption, not measured
A3: Average session minutes | B3: 10 | C3: Active sessions, not background tabs
A4: Sessions per daily active user | B4: 2 | C4: Assumption
A5: DAU / MAU ratio | B5: 0.2 | C5: 20% of monthly active users visit on an average day
A6: Monthly active-user churn | B6: 0.1 | C6: Replacement acquisition included
A7: Paid share of gross MAU acquisition | B7: 0.7 | C7: Remaining 30% organic / partnerships; not guaranteed
A8: Cost per acquired monthly active user USD | B8: 3 | C8: Not cost per install; blended geography-dependent assumption
A9: Answered questions per DAU per day | B9: 2 | C9: No subscription cap assumed; no revenue assumed
A10: AI USD per answered question | B10: 0.04 | C10: Planning allowance using current Sonnet setup; not measured bill
A11: Answer latency seconds | B11: 20 | C11: Capacity assumption, not benchmark
A12: Cash contingency | B12: 0.2 | C12: 20% of operating expenses; not profit
A13: USD per SGD | B13: 0.78 | C13: Budget FX assumption, not spot quote
... A20: Accounting/bank admin monthly USD | B20: 400 | C20: Allowance; reduce if covered by confirmed OSOME bundle

Sheet Usage and Acquisition
A1: Month | B1: Peak online target | C1: Avg-month peak | D1: Average concurrent | E1: DAU | F1: MAU end target | G1: Gross new MAU | H1: Paid new MAU | I1: Ad spend USD | J1: Monthly answers | K1: AI USD | L1: Peak answer concurrency
A2: Nov 2026 | B2: 1000 | C2: =(B2+0)/2 -> 500 | D2: =C2/Assumptions!B2 -> 125 | E2: =D2*1440/Assumptions!B3/Assumptions!B4 -> 9000 | F2: =B2/Assumptions!B2*1440/Assumptions!B3/Assumptions!B4/Assumptions!B5 -> 90000 | G2: =MAX(0,F2-Assumptions!B16*(1-Assumptions!B6)) -> 90000 | H2: =G2*Assumptions!B7 -> 63000 | I2: =H2*Assumptions!B8 -> 189000 | J2: =E2*Assumptions!B9*30 -> 540000 | K2: =J2*Assumptions!B10 -> 21600 | L2: =B2/Assumptions!B3/60/Assumptions!B4*Assumptions!B9*Assumptions!B11 -> 33.333333
A3: Dec 2026 | B3: 2000 | C3: =(B3+B2)/2 -> 1500 | D3: =C3/Assumptions!B2 -> 375 | E3: =D3*1440/Assumptions!B3/Assumptions!B4 -> 27000 | F3: =B3/Assumptions!B2*1440/Assumptions!B3/Assumptions!B4/Assumptions!B5 -> 180000 | G3: =MAX(0,F3-F2*(1-Assumptions!B6)) -> 99000 | H3: =G3*Assumptions!B7 -> 69300 | I3: =H3*Assumptions!B8 -> 207900 | J3: =E3*Assumptions!B9*31 -> 1674000 | K3: =J3*Assumptions!B10 -> 66960 | L3: =B3/Assumptions!B3/60/Assumptions!B4*Assumptions!B9*Assumptions!B11 -> 66.666667
A4: Jan 2027 | B4: 4000 | C4: =(B4+B3)/2 -> 3000 | D4: =C4/Assumptions!B2 -> 750 | E4: =D4*1440/Assumptions!B3/Assumptions!B4 -> 54000 | F4: =B4/Assumptions!B2*1440/Assumptions!B3/Assumptions!B4/Assumptions!B5 -> 360000 | G4: =MAX(0,F4-F3*(1-Assumptions!B6)) -> 198000 | H4: =G4*Assumptions!B7 -> 138600 | I4: =H4*Assumptions!B8 -> 415800 | J4: =E4*Assumptions!B9*31 -> 3348000 | K4: =J4*Assumptions!B10 -> 133920 | L4: =B4/Assumptions!B3/60/Assumptions!B4*Assumptions!B9*Assumptions!B11 -> 133.33333
A5: Feb 2027 | B5: 8000 | C5: =(B5+B4)/2 -> 6000 | D5: =C5/Assumptions!B2 -> 1500 | E5: =D5*1440/Assumptions!B3/Assumptions!B4 -> 108000 | F5: =B5/Assumptions!B2*1440/Assumptions!B3/Assumptions!B4/Assumptions!B5 -> 720000 | G5: =MAX(0,F5-F4*(1-Assumptions!B6)) -> 396000 | H5: =G5*Assumptions!B7 -> 277200 | I5: =H5*Assumptions!B8 -> 831600 | J5: =E5*Assumptions!B9*28 -> 6048000 | K5: =J5*Assumptions!B10 -> 241920 | L5: =B5/Assumptions!B3/60/Assumptions!B4*Assumptions!B9*Assumptions!B11 -> 266.66667
A6: Mar 2027 | B6: 16000 | C6: =(B6+B5)/2 -> 12000 | D6: =C6/Assumptions!B2 -> 3000 | E6: =D6*1440/Assumptions!B3/Assumptions!B4 -> 216000 | F6: =B6/Assumptions!B2*1440/Assumptions!B3/Assumptions!B4/Assumptions!B5 -> 1440000 | G6: =MAX(0,F6-F5*(1-Assumptions!B6)) -> 792000 | H6: =G6*Assumptions!B7 -> 554400 | I6: =H6*Assumptions!B8 -> 1663200 | J6: =E6*Assumptions!B9*31 -> 13392000 | K6: =J6*Assumptions!B10 -> 535680 | L6: =B6/Assumptions!B3/60/Assumptions!B4*Assumptions!B9*Assumptions!B11 -> 533.33333

Sheet Legal and Setup
A1: Item | B1: Nov 2026 USD | C1: Dec | D1: Jan | E1: Feb | F1: Mar | G1: Basis / inclusion
A2: OSOME SG incorporation + foreign-founder compliance | B2: =ROUND(Assumptions!B15*Assumptions!B13*(1+Assumptions!B14),2) -> 3206.95 | C2: 0 | D2: 0 | E2: 0 | F2: 0 | G2: Indicative starting bundle; first-year nominee, secretary and registered address. Confirm ACRA fees, accounting scope and tax with OSOME.
A3: Legal documents / privacy / PDPA / religious-content review | B3: 2000 | C3: 500 | D3: 0 | E3: 0 | F3: 0 | G3: Professional-services allowance; not an official fee
A4: Bank opening/KYC assistance | B4: 300 | C4: 0 | D4: 0 | E4: 0 | F4: 0 | G4: Allowance, not bank application fee; approval subject to KYC
A5: Stripe registration fee | B5: 0 | C5: 0 | D5: 0 | E5: 0 | F5: 0 | G5: No standard setup fee; technical integration included in Tech
A6: Standard D-U-N-S registration | B6: 0 | C6: 0 | D6: 0 | E6: 0 | F6: 0 | G6: Free standard route; expedited third-party fees excluded
A7: Google Play developer registration | B7: 25 | C7: 0 | D7: 0 | E7: 0 | F7: 0 | G7: Official one-time USD fee
A8: Apple Developer annual membership | B8: 99 | C8: 0 | D8: 0 | E8: 0 | F8: 0 | G8: Official annual USD fee; enrollment subject to verification
A9: Store listing, privacy forms and submission assistance | B9: 0 | C9: 800 | D9: 400 | E9: 0 | F9: 0 | G9: Service allowance; development/testing in Tech; no invented per-app publishing fee
A10: Accounting/tax filings and bank admin allowance | B10: =Assumptions!B20 -> 400 | C10: =Assumptions!B20 -> 400 | D10: =Assumptions!B20 -> 400 | E10: =Assumptions!B20 -> 400 | F10: =Assumptions!B20 -> 400 | G10: Not a tax provision. Reconcile OSOME accounting inclusion before purchase
A11: Total | B11: =SUM(B2:B10) -> 6030.95 | C11: =SUM(C2:C10) -> 1700 | D11: =SUM(D2:D10) -> 800 | E11: =SUM(E2:E10) -> 400 | F11: =SUM(F2:F10) -> 400 | G11: Paid cash outlay; no deposits counted as expenses

Sheet Read Me
A1: READ FIRST | B1: Planning interpretation and scope
A2: Period | B2: November 2026–March 2027 inferred from uploaded month headings and current date.
A3: Target | B3: 16,000 peak concurrent online users by March, NOT 16,000 registered users or simultaneous AI requests.
A4: Acquisition model | B4: Peak/average ratio 4, 10-minute sessions, 2 sessions/DAU, DAU/MAU 20%. March requires 1.44m MAU and 288k end-state DAU under these assumptions.
A5: Advertising | B5: $3 per acquired monthly active user, 70% paid share, 10% monthly MAU churn. CAC and organic share are unvalidated; ads cannot guarantee concurrent attendance.
A6: Usage | B6: Two answers/DAU/day. Monthly cost uses average of previous/current peak target, including ramp from zero in November. March average DAU 216k; full run-rate DAU 288k.
A7: Capacity | B7: 16k peak sessions imply about 533 simultaneously generating answers at 20-second latency under the assumed question rate. Current app capacity is NOT verified; quotas, distributed admission control and load testing required.
A8: AI cost | B8: $0.04/answer budget, not measured unit cost. No assumption that all knowledge documents or training rows are sent per request. March full-target run-rate: 17.856m answers / 31 days, $714,240 AI.
A9: Tech vs maintenance | B9: Tech: engineering new features, mobile apps, capacity controls and payment integration. Maintenance: separate ongoing bugs, QA, security and on-call. HR excludes these technical roles.
A10: Legal scope | B10: First-year incorporation/compliance cash outlay in November; no duplicate nominee/secretary/address charge. Accounting allowance may overlap package: confirm quote and adjust.
A11: Bank / capital | B11: Bank approval and Stripe activation are not guaranteed. Restricted minimum balances, paid-up capital, and refundable deposits are assets, not expenses. Hold a separate provisional $2,000 liquidity buffer; bank-dependent and excluded from expense total.
A12: Payment fees | B12: Base model assumes no receipts, hence $0 processing fees. If charging users: add Stripe/FX/refund/chargeback fees on web sales OR applicable store commission on store-billed sales; do not double count both on the same sale.
... A18: Immediate next gate | B18: Validate 30-day cost per answer, retention, paid-acquisition CAC and load-test performance before scaling spend. Nothing in this workbook changes the app or purchases services.

Sheet Sensitivity
A1: Five-month sensitivity | B1: AI cost/answer USD | C1: Paid MAU CAC USD | D1: Cash incl. 20% reserve USD | E1: Interpretation
A2: Lower-cost case | B2: 0.02 | C2: 1.5 | D2: ='Monthly Plan'!H22+(SUM('Usage and Acquisition'!J2:J6)*(B2-Assumptions!B10)+SUM('Usage and Acquisition'!H2:H6)*(C2-Assumptions!B8)*1.08)*(1+Assumptions!B12) -> 3071369.9 | E2: Not guaranteed; all traffic and fixed assumptions unchanged
A3: Base | B3: 0.04 | C3: 3 | D3: ='Monthly Plan'!H22+(SUM('Usage and Acquisition'!J2:J6)*(B3-Assumptions!B10)+SUM('Usage and Acquisition'!H2:H6)*(C3-Assumptions!B8)*1.08)*(1+Assumptions!B12) -> 5814677.9 | E3: Working budget
A4: Higher-cost case | B4: 0.06 | C4: 6 | D4: ='Monthly Plan'!H22+(SUM('Usage and Acquisition'!J2:J6)*(B4-Assumptions!B10)+SUM('Usage and Acquisition'!H2:H6)*(C4-Assumptions!B8)*1.08)*(1+Assumptions!B12) -> 10701246 | E4: Not a worst-case ceiling

Sheet Sources
A1: Source (checked 22 Sep 2026) | B1: URL | C1: Use / limitation
A2: OSOME nominee director packages | B2: https://osome.com/sg/nominee-director/ | C2: Starting SGD 3,772 bundle; binding quote and tax inclusions required
A3: Apple membership | B3: https://developer.apple.com/programs/whats-included/ | C3: USD 99 annual; commissions depend on eligibility
A4: Apple D-U-N-S | B4: https://developer.apple.com/support/D-U-N-S/ | C4: Standard organization number free
A5: Google Play registration | B5: https://support.google.com/googleplay/android-developer/answer/6112435 | C5: USD 25 one-time
A6: Stripe Singapore | B6: https://stripe.com/sg/pricing | C6: No setup/monthly fee; transaction charges depend on method/currency
A7: Replit AI integration | B7: https://docs.replit.com/features/integrations/replit-ai-integrations | C7: Provider public API prices; actual consumption billed
A8: Replit usage billing | B8: https://docs.replit.com/billing/about-usage-based-billing | C8: Compute/database/transfer depend on usage; workbook uses allowance, not quote
A9: Claude Sonnet 4.6 | B9: https://www.anthropic.com/news/claude-sonnet-4-6 | C9: Prior pricing basis $3 input/$15 output per million; cost per answer is assumption
A10: All other costs | B10: Management planning estimates | C10: Not supplier quotes: geography, hiring model and commercial rights change costs
