Workbook

Sheet Summary
A1: IQRA Assistant — Year-1 Scale-Up Budget
A2: Prepared by the CTO for the founder · Target: 1,000,000+ users & 100,000 books · Currency: BDT (USD shown)
A4: Year-1 total (with user ramp) | C4: Steady-state annual run-rate (full 1M) | E4: CTO cost per hour (fully-loaded)
A5: =Timeline!I15*Assumptions!B5 | C5: =(Team!G13+'AI & LLM'!B9+Infrastructure!C10+Knowledge!B7)*Assumptions!B5 | E5: ='CTO Rate'!B9
A6: =Timeline!I15 | C6: =(Team!G13+'AI & LLM'!B9+Infrastructure!C10+Knowledge!B7) | E6: ='CTO Rate'!B9/Assumptions!B5
A8: Annual cost by category (steady-state run-rate)
A9: Category | B9: Annual (USD) | C9: Annual (BDT) | D9: % of total
A10: Team & salaries | B10: =Team!G13 | C10: =B10*Assumptions!B5 | D10: =B10/(Team!G13+'AI & LLM'!B9+Infrastructure!C10+Knowledge!B7)
A11: AI / LLM (Claude) | B11: ='AI & LLM'!B9 | C11: =B11*Assumptions!B5 | D11: =B11/(Team!G13+'AI & LLM'!B9+Infrastructure!C10+Knowledge!B7)
A12: Infrastructure | B12: =Infrastructure!C10 | C12: =B12*Assumptions!B5 | D12: =B12/(Team!G13+'AI & LLM'!B9+Infrastructure!C10+Knowledge!B7)
A13: Knowledge (storage) | B13: =Knowledge!B7 | C13: =B13*Assumptions!B5 | D13: =B13/(Team!G13+'AI & LLM'!B9+Infrastructure!C10+Knowledge!B7)
A14: TOTAL run-rate | B14: =SUM(B10:B13) | C14: =SUM(C10:C13) | D14: =SUM(D10:D13)
A16: Key metrics
A17: Registered users (target) | B17: =Assumptions!B7
A18: Monthly active users | B18: ='AI & LLM'!B4
A19: Chat queries per year | B19: ='AI & LLM'!B6
A20: Books integrated | B20: =Assumptions!B16
A21: Knowledge storage (GB) | B21: =Knowledge!B4
A22: Total headcount | B22: =Team!C13
A24: • How to read this: 'Year-1 total' assumes users ramp up over 12 months (realistic first-year spend).
A25: • 'Steady-state run-rate' is the annual cost once you are actually at the full 1,000,000-user scale.
A26: • Every figure is driven by the Assumptions sheet — change an input there and all totals recompute.
A27: • Biggest cost driver is AI/LLM at scale; see the AI & LLM sheet for levers to reduce it.

Sheet Assumptions
A1: IQRA Assistant — Year-1 Scale-Up Cost Model
A2: Every input below is editable. Totals on all other sheets update automatically.
A3: Parameter | B3: Value | C3: Unit / Note
A4: General
A5: USD → BDT exchange rate | B5: 120 | C5: BDT per 1 USD
A6: Users & Usage (Year-1 target)
A7: Registered users (target) | B7: 1000000 | C7: users
A8: Monthly active users (% of registered) | B8: 0.2 | C8: % actually chatting each month
A9: Avg chat queries per active user / month | B9: 15 | C9: queries / month
A10: AI / LLM (Claude, per query)
A11: Input tokens per query (prompt + retrieved context) | B11: 4000 | C11: tokens
A12: Output tokens per query (the answer) | B12: 700 | C12: tokens
A13: LLM input price | B13: 3 | C13: USD per 1,000,000 tokens
A14: LLM output price | B14: 15 | C14: USD per 1,000,000 tokens
A15: Knowledge base (100,000 books)
A16: Books to integrate | B16: 100000 | C16: books
A17: Average file size per book | B17: 10 | C17: MB
A18: Search chunks generated per book | B18: 137 | C18: chunks (drives DB size)
A19: Object-storage price | B19: 0.02 | C19: USD per GB / month
A20: One-time ingestion compute (extract + chunk 100k books) | B20: 4000 | C20: USD (one-time, month 1)
A21: Team basis (Bangladesh)
A22: Working days per month | B22: 22 | C22: days
A23: Working hours per day | B23: 8 | C23: hours
A24: Employer overhead multiplier (benefits, tax, equipment, office) | B24: 1.2 | C24: × base salary
A25: Infrastructure (monthly, USD)
A26: App servers / hosting (autoscale for 1M users) | B26: 2000 | C26: USD / month
A27: Managed PostgreSQL (scaled; FTS over ~13.7M chunks) | B27: 1500 | C27: USD / month
A28: Bandwidth / CDN | B28: 300 | C28: USD / month
A29: Transactional email (Resend) | B29: 200 | C29: USD / month
A30: Monitoring / logging / error tracking | B30: 200 | C30: USD / month
A31: Domain, SSL, misc SaaS | B31: 50 | C31: USD / month

Sheet Team
A1: Team & Salaries (Bangladesh)
A2: Salaries in BDT / month. Annual loaded cost includes the employer overhead multiplier from Assumptions.
A3: Role | B3: Monthly salary (BDT) | C3: Count | D3: Monthly total (BDT) | E3: Annual base (BDT) | F3: Annual loaded (BDT) | G3: Annual loaded (USD)
A4: Chief Technology Officer (you) | B4: 400000 | C4: 1 | D4: =B4*C4 | E4: =D4*12 | F4: =E4*Assumptions!B24 | G4: =F4/Assumptions!B5
A5: Senior Backend Engineer | B5: 180000 | C5: 2 | D5: =B5*C5 | E5: =D5*12 | F5: =E5*Assumptions!B24 | G5: =F5/Assumptions!B5
A6: Frontend Engineer | B6: 160000 | C6: 2 | D6: =B6*C6 | E6: =D6*12 | F6: =E6*Assumptions!B24 | G6: =F6/Assumptions!B5
A7: DevOps / SRE Engineer | B7: 200000 | C7: 1 | D7: =B7*C7 | E7: =D7*12 | F7: =E7*Assumptions!B24 | G7: =F7/Assumptions!B5
A8: QA Engineer | B8: 120000 | C8: 1 | D8: =B8*C8 | E8: =D8*12 | F8: =E8*Assumptions!B24 | G8: =F8/Assumptions!B5
A9: Knowledge-Ops Lead | B9: 150000 | C9: 1 | D9: =B9*C9 | E9: =D9*12 | F9: =E9*Assumptions!B24 | G9: =F9/Assumptions!B5
A10: Content Specialist (book curation) | B10: 60000 | C10: 3 | D10: =B10*C10 | E10: =D10*12 | F10: =E10*Assumptions!B24 | G10: =F10/Assumptions!B5
A11: Community / Support | B11: 80000 | C11: 1 | D11: =B11*C11 | E11: =D11*12 | F11: =E11*Assumptions!B24 | G11: =F11/Assumptions!B5
A12: Product Manager | B12: 150000 | C12: 1 | D12: =B12*C12 | E12: =D12*12 | F12: =E12*Assumptions!B24 | G12: =F12/Assumptions!B5
A13: TOTAL | C13: =SUM(C4:C12) | D13: =SUM(D4:D12) | E13: =SUM(E4:E12) | F13: =SUM(F4:F12) | G13: =SUM(G4:G12)

Sheet CTO Rate
A1: CTO Cost per Hour
A2: Fully-loaded = salary × employer overhead. This is the true cost to the venture per CTO hour.
A4: CTO monthly salary (BDT) | B4: =Team!B4
A5: Working days per month | B5: =Assumptions!B22
A6: Working hours per day | B6: =Assumptions!B23
A7: Working hours per month | B7: =Assumptions!B22*Assumptions!B23
A8: Base cost per hour (BDT) | B8: =Team!B4/B7
A9: Fully-loaded cost per hour (BDT) | B9: =B8*Assumptions!B24
A10: Base cost per hour (USD) | B10: =B8/Assumptions!B5
A11: Fully-loaded cost per hour (USD) | B11: =B9/Assumptions!B5
A13: CTO cost by engagement (fully-loaded)
A14: Engagement | B14: BDT | C14: USD
A15: Per hour | B15: =B9 | C15: =B9/Assumptions!B5
A16: Per day (8h) | B16: =B9*Assumptions!B23 | C16: =B9*Assumptions!B23/Assumptions!B5
A17: Per week (5 days) | B17: =B9*Assumptions!B23*5 | C17: =B9*Assumptions!B23*5/Assumptions!B5
A18: Per month | B18: =Team!B4*Assumptions!B24 | C18: =Team!B4*Assumptions!B24/Assumptions!B5
A19: Per year | B19: =Team!B4*Assumptions!B24*12 | C19: =Team!B4*Assumptions!B24*12/Assumptions!B5

Sheet AI & LLM
A1: AI / LLM Cost (Claude) — at full 1M scale
A2: This is the steady-state run-rate assuming the full user target is active. The Timeline sheet ramps this up over the year.
A4: Monthly active users (MAU) | B4: =Assumptions!B7*Assumptions!B8
A5: Queries per month | B5: =B4*Assumptions!B9
A6: Queries per year | B6: =B5*12
A7: Cost per query (USD) | B7: =Assumptions!B11/1000000*Assumptions!B13+Assumptions!B12/1000000*Assumptions!B14
A8: LLM cost per month (USD) | B8: =B5*B7
A9: LLM cost per year (USD) | B9: =B8*12
A10: LLM cost per year (BDT) | B10: =B9*Assumptions!B5
A12: Sensitivity — annual LLM cost by activity level
A13: Monthly active % | B13: MAU | C13: Annual LLM (USD) | D13: Annual LLM (BDT)
A14: 0.1 | B14: =Assumptions!B7*A14 | C14: =B14*Assumptions!B9*12*B7 | D14: =C14*Assumptions!B5
A15: 0.2 | B15: =Assumptions!B7*A15 | C15: =B15*Assumptions!B9*12*B7 | D15: =C15*Assumptions!B5
A16: 0.3 | B16: =Assumptions!B7*A16 | C16: =B16*Assumptions!B9*12*B7 | D16: =C16*Assumptions!B5
A18: Levers to cut this: cache repeated answers, use a cheaper model (e.g. Haiku) for simple queries, cap free-tier usage.

Sheet Knowledge
A1: Knowledge Integration — 100,000 books
A2: Storage + one-time ingestion. Human curation effort sits in the Team sheet (Knowledge-Ops Lead + Content Specialists).
A4: Total storage (GB) | B4: =Assumptions!B16*Assumptions!B17/1024
A5: Total search chunks (info) | B5: =Assumptions!B16*Assumptions!B18
A6: Storage cost per month (USD) | B6: =B4*Assumptions!B19
A7: Storage cost per year (USD) | B7: =B6*12
A8: One-time ingestion compute (USD) | B8: =Assumptions!B20
A9: Year-1 knowledge cost (USD) | B9: =B7+B8
A10: Run-rate annual knowledge cost (USD) | B10: =B7
A11: Year-1 knowledge cost (BDT) | B11: =B9*Assumptions!B5

Sheet Infrastructure
A1: Infrastructure (excl. AI & knowledge storage)
A3: Item | B3: Monthly (USD) | C3: Annual (USD) | D3: Annual (BDT)
A4: App servers / hosting (autoscale) | B4: =Assumptions!B26 | C4: =B4*12 | D4: =C4*Assumptions!B5
A5: Managed PostgreSQL (scaled) | B5: =Assumptions!B27 | C5: =B5*12 | D5: =C5*Assumptions!B5
A6: Bandwidth / CDN | B6: =Assumptions!B28 | C6: =B6*12 | D6: =C6*Assumptions!B5
A7: Transactional email (Resend) | B7: =Assumptions!B29 | C7: =B7*12 | D7: =C7*Assumptions!B5
A8: Monitoring / logging | B8: =Assumptions!B30 | C8: =B8*12 | D8: =C8*Assumptions!B5
A9: Domain, SSL, misc SaaS | B9: =Assumptions!B31 | C9: =B9*12 | D9: =C9*Assumptions!B5
A10: TOTAL | B10: =SUM(B4:B9) | C10: =SUM(C4:C9) | D10: =SUM(D4:D9)

Sheet Timeline
A1: 12-Month Cash Timeline (with user ramp)
A2: Active users ramp linearly to target by month 12. Team & infra are fixed; ingestion one-time hits month 1.
A3: Month | B3: Active users | C3: LLM (USD) | D3: Infra (USD) | E3: Team (USD) | F3: Knowledge (USD) | G3: Total (USD) | H3: Total (BDT) | I3: Cumulative (USD)
A4: 1 | B4: =Assumptions!B7*Assumptions!B8*1/12 | C4: =B4*Assumptions!B9*'AI & LLM'!B7 | D4: =Infrastructure!B10 | E4: =Team!G13/12 | F4: =Knowledge!B6+Knowledge!B8 | G4: =C4+D4+E4+F4 | H4: =G4*Assumptions!B5 | I4: =G4
A5: 2 | B5: =Assumptions!B7*Assumptions!B8*2/12 | C5: =B5*Assumptions!B9*'AI & LLM'!B7 | D5: =Infrastructure!B10 | E5: =Team!G13/12 | F5: =Knowledge!B6 | G5: =C5+D5+E5+F5 | H5: =G5*Assumptions!B5 | I5: =I4+G5
A6: 3 | B6: =Assumptions!B7*Assumptions!B8*3/12 | C6: =B6*Assumptions!B9*'AI & LLM'!B7 | D6: =Infrastructure!B10 | E6: =Team!G13/12 | F6: =Knowledge!B6 | G6: =C6+D6+E6+F6 | H6: =G6*Assumptions!B5 | I6: =I5+G6
A7: 4 | B7: =Assumptions!B7*Assumptions!B8*4/12 | C7: =B7*Assumptions!B9*'AI & LLM'!B7 | D7: =Infrastructure!B10 | E7: =Team!G13/12 | F7: =Knowledge!B6 | G7: =C7+D7+E7+F7 | H7: =G7*Assumptions!B5 | I7: =I6+G7
A8: 5 | B8: =Assumptions!B7*Assumptions!B8*5/12 | C8: =B8*Assumptions!B9*'AI & LLM'!B7 | D8: =Infrastructure!B10 | E8: =Team!G13/12 | F8: =Knowledge!B6 | G8: =C8+D8+E8+F8 | H8: =G8*Assumptions!B5 | I8: =I7+G8
A9: 6 | B9: =Assumptions!B7*Assumptions!B8*6/12 | C9: =B9*Assumptions!B9*'AI & LLM'!B7 | D9: =Infrastructure!B10 | E9: =Team!G13/12 | F9: =Knowledge!B6 | G9: =C9+D9+E9+F9 | H9: =G9*Assumptions!B5 | I9: =I8+G9
A10: 7 | B10: =Assumptions!B7*Assumptions!B8*7/12 | C10: =B10*Assumptions!B9*'AI & LLM'!B7 | D10: =Infrastructure!B10 | E10: =Team!G13/12 | F10: =Knowledge!B6 | G10: =C10+D10+E10+F10 | H10: =G10*Assumptions!B5 | I10: =I9+G10
A11: 8 | B11: =Assumptions!B7*Assumptions!B8*8/12 | C11: =B11*Assumptions!B9*'AI & LLM'!B7 | D11: =Infrastructure!B10 | E11: =Team!G13/12 | F11: =Knowledge!B6 | G11: =C11+D11+E11+F11 | H11: =G11*Assumptions!B5 | I11: =I10+G11
A12: 9 | B12: =Assumptions!B7*Assumptions!B8*9/12 | C12: =B12*Assumptions!B9*'AI & LLM'!B7 | D12: =Infrastructure!B10 | E12: =Team!G13/12 | F12: =Knowledge!B6 | G12: =C12+D12+E12+F12 | H12: =G12*Assumptions!B5 | I12: =I11+G12
A13: 10 | B13: =Assumptions!B7*Assumptions!B8*10/12 | C13: =B13*Assumptions!B9*'AI & LLM'!B7 | D13: =Infrastructure!B10 | E13: =Team!G13/12 | F13: =Knowledge!B6 | G13: =C13+D13+E13+F13 | H13: =G13*Assumptions!B5 | I13: =I12+G13
A14: 11 | B14: =Assumptions!B7*Assumptions!B8*11/12 | C14: =B14*Assumptions!B9*'AI & LLM'!B7 | D14: =Infrastructure!B10 | E14: =Team!G13/12 | F14: =Knowledge!B6 | G14: =C14+D14+E14+F14 | H14: =G14*Assumptions!B5 | I14: =I13+G14
A15: 12 | B15: =Assumptions!B7*Assumptions!B8*12/12 | C15: =B15*Assumptions!B9*'AI & LLM'!B7 | D15: =Infrastructure!B10 | E15: =Team!G13/12 | F15: =Knowledge!B6 | G15: =C15+D15+E15+F15 | H15: =G15*Assumptions!B5 | I15: =I14+G15
